{"appleSKU":"","appleTeamID":"","enableCodelessAutoInitialization":true,"products":[{"id":"com.lttdg.removeads","type":1,"storeIDs":[],"defaultDescription":{"googleLocale":4,"title":"","description":""},"screenshotPath":"","applePriceTier":0,"xiaomiPriceTier":0,"googlePrice":{"data":[0,0,0,0],"num":0.0},"pricingTemplateID":"","descriptions":[],"payouts":[]},{"id":"com.lttdg.unlocklevels","type":1,"storeIDs":[],"defaultDescription":{"googleLocale":4,"title":"","description":""},"screenshotPath":"","applePriceTier":0,"xiaomiPriceTier":0,"googlePrice":{"data":[0,0,0,0],"num":0.0},"pricingTemplateID":"","descriptions":[],"payouts":[]},{"id":"com.lttdg.unlocktrucks","type":1,"storeIDs":[],"defaultDescription":{"googleLocale":4,"title":"","description":""},"screenshotPath":"","applePriceTier":0,"xiaomiPriceTier":0,"googlePrice":{"data":[0,0,0,0],"num":0.0},"pricingTemplateID":"","descriptions":[],"payouts":[]},{"id":"com.lttdg.doubletime","type":1,"storeIDs":[],"defaultDescription":{"googleLocale":4,"title":"","description":""},"screenshotPath":"","applePriceTier":0,"xiaomiPriceTier":0,"googlePrice":{"data":[0,0,0,0],"num":0.0},"pricingTemplateID":"","descriptions":[],"payouts":[]},{"id":"com.lttdg.unlockallgame","type":1,"storeIDs":[],"defaultDescription":{"googleLocale":4,"title":"","description":""},"screenshotPath":"","applePriceTier":0,"xiaomiPriceTier":0,"googlePrice":{"data":[0,0,0,0],"num":0.0},"pricingTemplateID":"","descriptions":[],"payouts":[]}]}